[
    {"id":1,"title":"康师傅香辣牛肉面","price":5,"num":10,"kg":"82.5g","src":"../assets/images/sp.jpg"},
    {"id":2,"title":"康师傅香辣牛肉面","price":5,"num":10,"kg":"82.5g","src":"../assets/images/sp.jpg"},
    {"id":3,"title":"康师傅香辣牛肉面","price":5,"num":10,"kg":"82.5g","src":"../assets/images/sp.jpg"},
    {"id":4,"title":"康师傅香辣牛肉面","price":5,"num":10,"kg":"82.5g","src":"../assets/images/sp.jpg"},
    {"id":5,"title":"康师傅香辣牛肉面","price":5,"num":10,"kg":"82.5g","src":"../assets/images/sp.jpg"},
    {"id":6,"title":"康师傅香辣牛肉面","price":5,"num":10,"kg":"82.5g","src":"../assets/images/sp.jpg"},
    {"id":7,"title":"康师傅香辣牛肉面","price":5,"num":10,"kg":"82.5g","src":"../assets/images/sp.jpg"},
    {"id":8,"title":"康师傅香辣牛肉面","price":5,"num":10,"kg":"82.5g","src":"../assets/images/sp.jpg"},
    {"id":9,"title":"康师傅香辣牛肉面","price":5,"num":10,"kg":"82.5g","src":"../assets/images/sp.jpg"},
    {"id":10,"title":"康师傅香辣牛肉面","price":5,"num":10,"kg":"82.5g","src":"../assets/images/sp.jpg"},
    {"id":11,"title":"康师傅香辣牛肉面","price":5,"num":10,"kg":"82.5g","src":"../assets/images/sp.jpg"},
    {"id":12,"title":"康师傅香辣牛肉面","price":5,"num":10,"kg":"82.5g","src":"../assets/images/sp.jpg"},
    {"id":13,"title":"康师傅香辣牛肉面","price":5,"num":10,"kg":"82.5g","src":"../assets/images/sp.jpg"},
    {"id":14,"title":"康师傅香辣牛肉面","price":5,"num":10,"kg":"82.5g","src":"../assets/images/sp.jpg"},
    {"id":15,"title":"康师傅香辣牛肉面","price":5,"num":10,"kg":"82.5g","src":"../assets/images/sp.jpg"}
]